pybow/__init__.py
pybow/bow.py
pybow/cli.py
pybow/props.py
pybow/analysis/__init__.py
pybow/analysis/beck64.py
pybow/analysis/junk13.py
pybow/data/__init__.py
pybow/data/data.py
pybow-0.1.dist-info/METADATA
pybow-0.1.dist-info/RECORD
pybow-0.1.dist-info/WHEEL
pybow-0.1.dist-info/entry_points.txt
pybow-0.1.dist-info/top_level.txt
