Metadata-Version: 2.1
Name: pybow
Version: 0.1
Summary: A collection of archery-focused calculation methods
Home-page: https://gitlab.com/gekitsu/pybow
Author: R. Kretz
License: UNKNOWN
Keywords: archery archaeology bowyery
Platform: UNKNOWN
Classifier: Development Status :: 3 - Alpha
Classifier: Intended Audience :: Science/Research
Classifier: Topic :: Scientific/Engineering
Classifier: License :: OSI Approved :: GNU Lesser General Public License v3 or later (LGPLv3+)
Classifier: Programming Language :: Python :: 3
Classifier: Programming Language :: Python :: 3.6
Classifier: Programming Language :: Python :: 3.7
Provides-Extra: dev
Provides-Extra: test
Requires-Dist: numpy
Requires-Dist: pandas
Requires-Dist: ruamel.yaml
Provides-Extra: dev
Requires-Dist: sphinx; extra == 'dev'
Provides-Extra: test
Requires-Dist: pytest; extra == 'test'
